{
  "$schema": "http://json.schemastore.org/template",
  "author": "Linn Products",
  "classifications": [ "Solution" ],
  "name": "Linn.Template",
  "identity": "Linn.Template",
  "groupIdentity": "Linn.Template",
  "shortName": "linntemplate",
  "tags": {
    "language": "C#",
    "type": "project"
  },
  "sourceName": "Linn.Template",
  "preferNameDirectory": true,
  "sources": [
    {
      "modifiers": [
        {
          "exclude": [
            ".vs/**",
            ".git",
            "src/Service.Host/node_modules/**"
          ]
        }
      ]
    }
  ],
  "symbols": {
    "solutionName": {
      "type": "parameter",
      "dataType": "string",
      "fileRename": "Template.sln"
    }
  }
}